liecasadi/__init__.py
liecasadi/dualquaternion.py
liecasadi/quaternion.py
liecasadi/se3.py
liecasadi/so3.py
liecasadi/hints/__init__.py
liecasadi-0.0.7.dist-info/LICENSE
liecasadi-0.0.7.dist-info/METADATA
liecasadi-0.0.7.dist-info/WHEEL
liecasadi-0.0.7.dist-info/top_level.txt
liecasadi-0.0.7.dist-info/RECORD
