Metadata-Version: 2.2
Name: liecasadi
Version: 0.0.7
Summary: Rigid transform using Lie groups, written in CasADi!
Author-email: Giuseppe L'Erario <gl.giuseppelerario@gmail.com>
License: BSD 3-Clause License
Keywords: robotics,automatic-differentiation,optimization,casadi,lie-groups,manifolds
Requires-Python: >=3.10
License-File: LICENSE
Requires-Dist: numpy>=1.21
Requires-Dist: casadi
Provides-Extra: test
Requires-Dist: pytest; extra == "test"
Requires-Dist: manifpy; extra == "test"
Requires-Dist: scipy; extra == "test"
